xia_broadcast_listener/__init__.py
xia_broadcast_listener/listener.cpython-39-darwin.so
xia_broadcast_listener-0.1.5.dist-info/LICENSE.txt
xia_broadcast_listener-0.1.5.dist-info/METADATA
xia_broadcast_listener-0.1.5.dist-info/WHEEL
xia_broadcast_listener-0.1.5.dist-info/top_level.txt
xia_broadcast_listener-0.1.5.dist-info/RECORD
